more.jwtauth-0.14-py3.11-nspkg.pth
more/jwtauth/__init__.py
more/jwtauth/main.py
more/jwtauth/refresh.py
more/jwtauth/utils.py
more/jwtauth/tests/__init__.py
more/jwtauth/tests/handler.py
more/jwtauth/tests/test_cryptography.py
more/jwtauth/tests/test_jwtauth.py
more/jwtauth/tests/test_refresh.py
more/jwtauth/tests/keys/testkey_ec
more/jwtauth/tests/keys/testkey_ec.pub
more/jwtauth/tests/keys/testkey_rsa
more/jwtauth/tests/keys/testkey_rsa.pub
more.jwtauth-0.14.dist-info/LICENSE.txt
more.jwtauth-0.14.dist-info/METADATA
more.jwtauth-0.14.dist-info/WHEEL
more.jwtauth-0.14.dist-info/namespace_packages.txt
more.jwtauth-0.14.dist-info/top_level.txt
more.jwtauth-0.14.dist-info/RECORD
