Metadata-Version: 2.1
Name: more.jwtauth
Version: 0.14
Summary: JWT Access Auth Identity Policy for Morepath
Home-page: https://github.com/morepath/more.jwtauth
Author: Morepath developers
Author-email: morepath@googlegroups.com
License: BSD
Keywords: morepath JWT identity authentication
Classifier: Intended Audience :: Developers
Classifier: License :: OSI Approved :: BSD License
Classifier: Environment :: Web Environment
Classifier: Topic :: Software Development :: Libraries :: Application Frameworks
Classifier: Topic :: Internet :: WWW/HTTP :: WSGI
Classifier: Programming Language :: Python :: 3.8
Classifier: Programming Language :: Python :: 3.9
Classifier: Programming Language :: Python :: 3.10
Classifier: Programming Language :: Python :: 3.11
Classifier: Programming Language :: Python :: 3.12
Classifier: Programming Language :: Python :: Implementation :: PyPy
Classifier: Development Status :: 5 - Production/Stable
License-File: LICENSE.txt
Requires-Dist: morepath >=0.19
Requires-Dist: PyJWT ==2.8.0
Provides-Extra: coverage
Requires-Dist: pytest-cov ; extra == 'coverage'
Provides-Extra: crypto
Requires-Dist: cryptography >=3.4.0 ; extra == 'crypto'
Provides-Extra: lint
Requires-Dist: black ==22.3.0 ; extra == 'lint'
Requires-Dist: flake8 ==4.0.1 ; extra == 'lint'
Requires-Dist: pyupgrade ==2.34.0 ; extra == 'lint'
Requires-Dist: isort ==5.10.1 ; extra == 'lint'
Provides-Extra: test
Requires-Dist: pytest >=2.9.1 ; extra == 'test'
Requires-Dist: pytest-remove-stale-bytecode ; extra == 'test'
Requires-Dist: webtest ; extra == 'test'
Requires-Dist: pygments ; extra == 'test'
